[
    {"Period":"2019","Macbook Pro Laptop":"8035900","iPhone":"4792900","ThinkPad Laptop":"4127958.71999998","Google Phone":"3318600","27in 4K Gaming Monitor":"2434707.56999999","34in Ultrawide Monitor":"2355558.00999999","Apple Airpods Headphones":"2348550","Flatscreen TV":"1445400","Bose SoundSport Headphones":"1345265.46000001","27in FHD Monitor":"1131974.53000001","Vareebadd Phone":"826800","20in Monitor":"453818.740000001","LG Washing Machine":"399600","LG Dryer":"387600","Lightning Charging Cable":"347004.450000006","USB-C Charging Cable":"286453.450000008","Wired Headphones":"246430.470000003","AA Batteries (4-pack)":"106118.400000002","AAA Batteries (4-pack)":"92725.8799999969","Total":"34483365.68"},
    {"Period":"Jan","Macbook Pro Laptop":"397800","iPhone":"265300","ThinkPad Laptop":"216997.829999999","Google Phone":"190800","27in 4K Gaming Monitor":"121676.880000001","34in Ultrawide Monitor":"119316.860000001","Apple Airpods Headphones":"122100","Flatscreen TV":"72900","Bose SoundSport Headphones":"65893.4099999996","27in FHD Monitor":"62845.8099999998","Vareebadd Phone":"50000","20in Monitor":"23647.8500000001","LG Washing Machine":"25200","LG Dryer":"23400","Lightning Charging Cable":"17177.5500000003","USB-C Charging Cable":"15331.8500000003","Wired Headphones":"12961.1899999998","AA Batteries (4-pack)":"5468.16000000006","AAA Batteries (4-pack)":"4769.04999999989","Total":"1813586.44"},
    {"Period":"Feb","Macbook Pro Laptop":"469200","iPhone":"307300","ThinkPad Laptop":"274997.249999999","Google Phone":"228600","27in 4K Gaming Monitor":"166525.73","34in Ultrawide Monitor":"158835.82","Apple Airpods Headphones":"151800","Flatscreen TV":"93900","Bose SoundSport Headphones":"84091.5900000005","27in FHD Monitor":"71245.2499999999","Vareebadd Phone":"51600","20in Monitor":"27057.5400000001","LG Washing Machine":"24000","LG Dryer":"22800","Lightning Charging Cable":"22410.0500000005","USB-C Charging Cable":"19765.3000000005","Wired Headphones":"15335.2099999998","AA Batteries (4-pack)":"6662.40000000011","AAA Batteries (4-pack)":"5896.27999999985","Total":"2202022.42"},
    {"Period":"Mar","Macbook Pro Laptop":"644300","iPhone":"376600","ThinkPad Laptop":"344996.549999998","Google Phone":"277800","27in 4K Gaming Monitor":"186805.209999999","34in Ultrawide Monitor":"198354.779999999","Apple Airpods Headphones":"198300","Flatscreen TV":"108600","Bose SoundSport Headphones":"119788.020000002","27in FHD Monitor":"91193.9200000006","Vareebadd Phone":"69600","20in Monitor":"35856.7400000002","LG Washing Machine":"38400","LG Dryer":"29400","Lightning Charging Cable":"28001.3500000008","USB-C Charging Cable":"23230.8000000007","Wired Headphones":"19951.3600000002","AA Batteries (4-pack)":"8509.44000000019","AAA Batteries (4-pack)":"7412.20999999977","Total":"2807100.38"},
    {"Period":"Apr","Macbook Pro Laptop":"771800","iPhone":"485100","ThinkPad Laptop":"389996.099999998","Google Phone":"348000","27in 4K Gaming Monitor":"220734.339999999","34in Ultrawide Monitor":"248513.459999998","Apple Airpods Headphones":"227850","Flatscreen TV":"138000","Bose SoundSport Headphones":"128687.130000003","27in FHD Monitor":"110392.640000001","Vareebadd Phone":"88000","20in Monitor":"43226.07","LG Washing Machine":"36600","LG Dryer":"46800","Lightning Charging Cable":"35476.3500000006","USB-C Charging Cable":"27114.550000001","Wired Headphones":"24759.3500000007","AA Batteries (4-pack)":"10832.6400000003","AAA Batteries (4-pack)":"8787.60999999968","Total":"3390670.24"},
    {"Period":"May","Macbook Pro Laptop":"790500","iPhone":"448000","ThinkPad Laptop":"370996.289999998","Google Phone":"288000","27in 4K Gaming Monitor":"211374.579999999","34in Ultrawide Monitor":"206714.559999999","Apple Airpods Headphones":"204750","Flatscreen TV":"119700","Bose SoundSport Headphones":"117588.240000002","27in FHD Monitor":"103343.110000001","Vareebadd Phone":"74000","20in Monitor":"37506.5900000001","LG Washing Machine":"38400","LG Dryer":"45600","Lightning Charging Cable":"31021.250000001","USB-C Charging Cable":"24712.6000000008","Wired Headphones":"22493.2400000004","AA Batteries (4-pack)":"9154.5600000002","AAA Batteries (4-pack)":"8751.7299999997","Total":"3152606.75"},
    {"Period":"Jun","Macbook Pro Laptop":"605200","iPhone":"373100","ThinkPad Laptop":"313996.859999999","Google Phone":"234600","27in 4K Gaming Monitor":"175885.49","34in Ultrawide Monitor":"172895.45","Apple Airpods Headphones":"175050","Flatscreen TV":"110100","Bose SoundSport Headphones":"98290.1700000013","27in FHD Monitor":"85044.3300000004","Vareebadd Phone":"62000","20in Monitor":"35416.7800000002","LG Washing Machine":"33000","LG Dryer":"25800","Lightning Charging Cable":"25220.6500000007","USB-C Charging Cable":"20016.2500000005","Wired Headphones":"17673.2599999999","AA Batteries (4-pack)":"8048.64000000016","AAA Batteries (4-pack)":"6464.37999999981","Total":"2577802.26"},
    {"Period":"Jul","Macbook Pro Laptop":"625600","iPhone":"351400","ThinkPad Laptop":"318996.809999999","Google Phone":"246600","27in 4K Gaming Monitor":"188365.169999999","34in Ultrawide Monitor":"175555.38","Apple Airpods Headphones":"183000","Flatscreen TV":"119700","Bose SoundSport Headphones":"105989.400000002","27in FHD Monitor":"91043.9300000006","Vareebadd Phone":"58400","20in Monitor":"35966.7300000001","LG Washing Machine":"31200","LG Dryer":"33000","Lightning Charging Cable":"27074.4500000008","USB-C Charging Cable":"22095.5500000007","Wired Headphones":"18764.35","AA Batteries (4-pack)":"7952.64000000016","AAA Batteries (4-pack)":"7071.34999999978","Total":"2647775.76"},
    {"Period":"Aug","Macbook Pro Laptop":"508300","iPhone":"307300","ThinkPad Laptop":"273997.259999999","Google Phone":"216600","27in 4K Gaming Monitor":"171595.6","34in Ultrawide Monitor":"144396.2","Apple Airpods Headphones":"151350","Flatscreen TV":"99300","Bose SoundSport Headphones":"88091.1900000007","27in FHD Monitor":"73645.09","Vareebadd Phone":"57200","20in Monitor":"28707.3900000001","LG Washing Machine":"28800","LG Dryer":"27600","Lightning Charging Cable":"21572.8500000005","USB-C Charging Cable":"17470.9000000004","Wired Headphones":"15479.0899999998","AA Batteries (4-pack)":"7019.52000000013","AAA Batteries (4-pack)":"6042.78999999984","Total":"2244467.88"},
    {"Period":"Sep","Macbook Pro Laptop":"489600","iPhone":"277900","ThinkPad Laptop":"248997.509999999","Google Phone":"204600","27in 4K Gaming Monitor":"148586.19","34in Ultrawide Monitor":"144016.21","Apple Airpods Headphones":"145350","Flatscreen TV":"88200","Bose SoundSport Headphones":"82791.7200000005","27in FHD Monitor":"72445.17","Vareebadd Phone":"50400","20in Monitor":"30467.2300000002","LG Washing Machine":"27600","LG Dryer":"18000","Lightning Charging Cable":"21408.4000000005","USB-C Charging Cable":"19048.3000000005","Wired Headphones":"15598.9899999998","AA Batteries (4-pack)":"6800.64000000012","AAA Batteries (4-pack)":"5749.76999999986","Total":"2097560.13"},
    {"Period":"Oct","Macbook Pro Laptop":"892500","iPhone":"501200","ThinkPad Laptop":"460995.389999997","Google Phone":"358200","27in 4K Gaming Monitor":"281962.769999997","34in Ultrawide Monitor":"254973.289999998","Apple Airpods Headphones":"250650","Flatscreen TV":"157200","Bose SoundSport Headphones":"146485.350000002","27in FHD Monitor":"118642.090000002","Vareebadd Phone":"81200","20in Monitor":"47185.7099999999","LG Washing Machine":"36600","LG Dryer":"30000","Lightning Charging Cable":"38451.4000000001","USB-C Charging Cable":"31870.6500000012","Wired Headphones":"27265.260000001","AA Batteries (4-pack)":"11289.6000000003","AAA Batteries (4-pack)":"10055.3699999996","Total":"3736726.88"},
    {"Period":"Nov","Macbook Pro Laptop":"748000","iPhone":"465500","ThinkPad Laptop":"373996.259999998","Google Phone":"295800","27in 4K Gaming Monitor":"224244.249999999","34in Ultrawide Monitor":"209374.489999999","Apple Airpods Headphones":"226950","Flatscreen TV":"138000","Bose SoundSport Headphones":"125187.480000003","27in FHD Monitor":"107842.810000001","Vareebadd Phone":"70800","20in Monitor":"46195.8","LG Washing Machine":"31800","LG Dryer":"33600","Lightning Charging Cable":"33039.500000001","USB-C Charging Cable":"26959.2000000009","Wired Headphones":"23188.6600000005","AA Batteries (4-pack)":"10080.0000000002","AAA Batteries (4-pack)":"9044.74999999967","Total":"3199603.2"},
    {"Period":"Dec","Macbook Pro Laptop":"1093100","iPhone":"634200","ThinkPad Laptop":"538994.609999997","Google Phone":"429000","27in 4K Gaming Monitor":"336951.359999996","34in Ultrawide Monitor":"322611.509999996","Apple Airpods Headphones":"311400","Flatscreen TV":"199800","Bose SoundSport Headphones":"182381.759999998","27in FHD Monitor":"144290.380000001","Vareebadd Phone":"113600","20in Monitor":"62584.3099999997","LG Washing Machine":"48000","LG Dryer":"51600","Lightning Charging Cable":"46150.6499999987","USB-C Charging Cable":"38837.5000000001","Wired Headphones":"32960.5100000016","AA Batteries (4-pack)":"14300.1600000004","AAA Batteries (4-pack)":"12680.5899999994","Total":"4613443.33999999"}
    ]